nameko_cron/__init__.py
nameko_cron-0.1.0.dist-info/LICENSE.txt
nameko_cron-0.1.0.dist-info/METADATA
nameko_cron-0.1.0.dist-info/WHEEL
nameko_cron-0.1.0.dist-info/top_level.txt
nameko_cron-0.1.0.dist-info/RECORD
