Metadata-Version: 2.1
Name: nameko-cron
Version: 0.1.0
Summary: Nameko cron extension
Home-page: https://github.com/bradshjg/nameko-cron
Author: bradshjg
Author-email: james.g.bradshaw@gmail.com
License: UNKNOWN
Platform: UNKNOWN
Classifier: Programming Language :: Python :: 3
Classifier: Programming Language :: Python :: 3.6
Classifier: Programming Language :: Python :: 3.7
Classifier: Programming Language :: Python :: 3.8
Classifier: License :: OSI Approved :: MIT License
Classifier: Operating System :: OS Independent
Classifier: Topic :: Internet
Classifier: Topic :: Software Development :: Libraries :: Python Modules
Classifier: Intended Audience :: Developers
Requires-Python: >=3.6
Requires-Dist: croniter
Requires-Dist: nameko
Requires-Dist: pytz
